podqueue/__init__.py
podqueue/__main__.py
podqueue/main.py
podqueue/podqueue.egg-info/PKG-INFO
podqueue/podqueue.egg-info/SOURCES.txt
podqueue/podqueue.egg-info/dependency_links.txt
podqueue/podqueue.egg-info/requires.txt
podqueue/podqueue.egg-info/top_level.txt
podqueue-0.1.9.dist-info/LICENSE
podqueue-0.1.9.dist-info/METADATA
podqueue-0.1.9.dist-info/WHEEL
podqueue-0.1.9.dist-info/top_level.txt
podqueue-0.1.9.dist-info/RECORD
