Metadata-Version: 2.1
Name: podqueue
Version: 0.1.9
Summary: Automate the archiving of podcast feeds, including show notes and images.
Home-page: https://github.com/tquin/podqueue
Download-URL: https://pypi.org/project/podqueue/
Author: Tyler Quinlivan
Author-email: hello@tylerquinlivan.com
License: MIT
Keywords: podcast,podqueue,archive,download
Classifier: Programming Language :: Python :: 3
Classifier: License :: OSI Approved :: MIT License
Classifier: Operating System :: OS Independent
Requires-Python: >=3.6
License-File: LICENSE
Requires-Dist: feedparser >=6.0.8
Requires-Dist: requests >=2.22.0
